Workbook

Sheet balance_sheet
B1: Balance Sheet
C2: 46022 | D2: 45657 | E2: 45291 | F2: 44926
B3: Ordinary Shares Number | C3: 17305307303 | D3: 17446322177 | E3: 17446322177 | F3: 17461402631
B4: Share Issued | C4: 17305307303 | D4: 17446322177 | E4: 17446322177 | F4: 17461402631
B5: Total Debt | C5: 80848147000 | D5: 79729904000 | E5: 75253796000 | F5: 69838582000
B6: Tangible Book Value | C6: 192933511000 | D6: 185482343000 | E6: 160749817000 | F6: 163250009000
B7: Invested Capital | C7: 235580061000 | D7: 232875469000 | E7: 199086037000 | F7: 202468383000
B8: Working Capital | C8: -5607265000 | D8: 2603524000 | E8: 3523799000 | F8: 16847276000
B9: Net Tangible Assets | C9: 192933511000 | D9: 185482343000 | E9: 160749817000 | F9: 163250009000
B10: Capital Lease Obligations | C10: 80848147000 | D10: 79729904000 | E10: 75253796000 | F10: 69838582000
B11: Common Stock Equity | C11: 235580061000 | D11: 232875469000 | E11: 199086037000 | F11: 202468383000 | H11: check
B12: Total Capitalization | C12: 235580061000 | D12: 232875469000 | E12: 199086037000 | F12: 202468383000 | G12: assets | H12: =C38 -> 495273263000
B13: Total Equity Gross Minority Interest | C13: 235580061000 | D13: 232875469000 | E13: 199086037000 | F13: 202468383000 | G13: liabilities+equity | H13: =C20+C14 -> 495273263000
B14: Stockholders Equity | C14: 235580061000 | D14: 232875469000 | E14: 199086037000 | F14: 202468383000
B15: Other Equity Interest | C15: -10398225000 | D15: -11168314000 | E15: -12094876000 | F15: -8089592000
B16: Retained Earnings | C16: 180017034000 | D16: 167447963000 | E16: 151020031000 | F16: 146727023000
B17: Additional Paid In Capital | C17: 6230963000 | D17: 5906487000 | E17: 5640011000 | F17: 5289992000
B18: Capital Stock | C18: 45027866000 | D18: 45429160000 | E18: 45429160000 | F18: 45468428000
B19: Common Stock | C19: 45027866000 | D19: 45429160000 | E19: 45429160000 | F19: 45468428000
B20: Total Liabilities Net Minority Interest | C20: 259693202000 | D20: 261017596000 | E20: 237460579000 | F20: 216339988000
B21: Total Non Current Liabilities Net Minority Interest | C21: 89976490000 | D21: 90223852000 | E21: 81242066000 | F21: 78654234000
B22: Other Non Current Liabilities | C22: 13177000 | D22: 13408000 | E22: 7106000 | F22: 7906000
B23: Non Current Pension And Other Postretirement Benefit Plans | C23: 3623589000 | D23: 2997869000 | E23: 2327110000 | F23: 2278556000
B24: Tradeand Other Payables Non Current | C24: 8475751000 | D24: 9693357000 | E24: 5075163000 | F24: 6651033000
B25: Non Current Deferred Revenue | C25: 2202768000 | D25: 2524430000 | E25: 2891014000 | F25: 3389703000
... B70: Cash Financial | C70: 28586217000 | D70: 36513582000 | E70: 35743572000 | F70: 36008176000

Sheet income_statement
B1: Income Statement
C2: 46022 | D2: 45657 | E2: 45291 | F2: 44926
B3: Tax Effect Of Unusual Items | C3: -47673175 | D3: 47118288 | E3: -25021960 | F3: 17368224
B4: Tax Rate For Calcs | C4: 0.275 | D4: 0.219 | E4: 0.248 | F4: 0.227
B5: Normalized EBITDA | C5: 103118291000 | D5: 99949293000 | E5: 97121590000 | F5: 89699087000
B6: Total Unusual Items | C6: -173357000 | D6: 215152000 | E6: -100895000 | F6: 76512000
B7: Total Unusual Items Excluding Goodwill | C7: -173357000 | D7: 215152000 | E7: -100895000 | F7: 76512000
B8: Net Income From Continuing Operation Net Minority Interest | C8: 49890741000 | D8: 53827384000 | E8: 51589989000 | F8: 48974184000
B9: Reconciled Depreciation | C9: 24953131000 | D9: 22639474000 | E9: 20577439000 | F9: 19359205000
B10: Reconciled Cost Of Revenue | C10: 766399989000 | D10: 727034273000 | E10: 675964861000 | F10: 627771101000
B11: EBITDA | C11: 102944934000 | D11: 100164445000 | E11: 97020695000 | F11: 89775599000
B12: EBIT | C12: 77991803000 | D12: 77524971000 | E12: 76443256000 | F12: 70416394000
B13: Net Interest Income | C13: -9365332000 | D13: -7904238000 | E13: -4852035000 | F13: -5150071000
B14: Interest Expense | C14: 9115155000 | D14: 8593484000 | E14: 7836519000 | F14: 7049835000
... B46: Operating Revenue | C46: 1010803706000 | D46: 957524496000 | E46: 885739821000 | F46: 818225636000

Sheet Trends
B2: Income Statement | C2: 2 | D2: 3 | E2: 4 | F2: 5 | H2: Balance Sheet | I2: 2 | J2: 3 | K2: 4 | L2: 5
C3: 2025 | D3: 2024 | E3: 2023 | F3: 2022 | I3: 2025 | J3: 2024 | K3: 2023 | L3: 2022
B4: EBITDA | C4: =VLOOKUP($B4,income_statement!$B$2:$F$46,Trends!C$2,FALSE) -> 102944934000 | D4: =VLOOKUP($B4,income_statement!$B$2:$F$46,Trends!D$2,FALSE) -> 100164445000 | E4: =VLOOKUP($B4,income_statement!$B$2:$F$46,Trends!E$2,FALSE) -> 97020695000 | F4: =VLOOKUP($B4,income_statement!$B$2:$F$46,Trends!F$2,FALSE) -> 89775599000 | H4: Stockholders Equity | I4: =VLOOKUP($H4,balance_sheet!$B$2:$F$70,I$2,FALSE) -> 235580061000 | J4: =VLOOKUP($H$4,balance_sheet!$B$2:$F$70,J$2,FALSE) -> 232875469000 | K4: =VLOOKUP($H$4,balance_sheet!$B$2:$F$70,K$2,FALSE) -> 199086037000 | L4: =VLOOKUP($H$4,balance_sheet!$B$2:$F$70,L$2,FALSE) -> 202468383000
B5: Net Income | C5: =VLOOKUP($B5,income_statement!$B$2:$F$46,Trends!C$2,FALSE) -> 49890741000 | D5: =VLOOKUP($B5,income_statement!$B$2:$F$46,Trends!D$2,FALSE) -> 53827384000 | E5: =VLOOKUP($B5,income_statement!$B$2:$F$46,Trends!E$2,FALSE) -> 51589989000 | F5: =VLOOKUP($B5,income_statement!$B$2:$F$46,Trends!F$2,FALSE) -> 48974184000 | H5: Total Liabilities Net Minority Interest | I5: =VLOOKUP($H5,balance_sheet!$B$2:$F$70,I$2,FALSE) -> 259693202000 | J5: =VLOOKUP($H5,balance_sheet!$B$2:$F$70,J$2,FALSE) -> 261017596000 | K5: =VLOOKUP($H5,balance_sheet!$B$2:$F$70,K$2,FALSE) -> 237460579000 | L5: =VLOOKUP($H5,balance_sheet!$B$2:$F$70,L$2,FALSE) -> 216339988000
B6: Gross Profit | C6: =VLOOKUP($B6,income_statement!$B$2:$F$46,Trends!C$2,FALSE) -> 244403717000 | D6: =VLOOKUP($B6,income_statement!$B$2:$F$46,Trends!D$2,FALSE) -> 230490223000 | E6: =VLOOKUP($B6,income_statement!$B$2:$F$46,Trends!E$2,FALSE) -> 209774960000 | F6: =VLOOKUP($B6,income_statement!$B$2:$F$46,Trends!F$2,FALSE) -> 190454535000 | H6: Total Assets | I6: =VLOOKUP($H6,balance_sheet!$B$2:$F$70,I$2,FALSE) -> 495273263000 | J6: =VLOOKUP($H6,balance_sheet!$B$2:$F$70,J$2,FALSE) -> 493893065000 | K6: =VLOOKUP($H6,balance_sheet!$B$2:$F$70,K$2,FALSE) -> 436546616000 | L6: =VLOOKUP($H6,balance_sheet!$B$2:$F$70,L$2,FALSE) -> 418808371000
B7: Total Revenue | C7: =VLOOKUP($B7,income_statement!$B$2:$F$46,Trends!C$2,FALSE) -> 1010803706000 | D7: =VLOOKUP($B7,income_statement!$B$2:$F$46,Trends!D$2,FALSE) -> 957524496000 | E7: =VLOOKUP($B7,income_statement!$B$2:$F$46,Trends!E$2,FALSE) -> 885739821000 | F7: =VLOOKUP($B7,income_statement!$B$2:$F$46,Trends!F$2,FALSE) -> 818225636000
H8: Debt Metrics
B9: How efficient is WALMEX (WALMEX.MX)? | H9: How leveraged is Walmex?
B10: Net profit margin | C10: =C5/C7 -> 0.049357497 | D10: =D5/D7 -> 0.056215151 | E10: =E5/E7 -> 0.058245083 | F10: =F5/F7 -> 0.059854131 | H10: Debt to Equity | I10: =I5/I4 -> 1.1023565 | J10: =J5/J4 -> 1.1208462 | K10: =K5/K4 -> 1.1927536 | L10: =L5/L4 -> 1.0685125
B11: The percentage of revenue left as net income after all expenses are paid | H11: Ratio used to evaluate its financial leverage dividing total debt by equity
B13: ROE | C13: =C5/I4 -> 0.21177828 | D13: =D5/J4 -> 0.23114235 | E13: =E5/K4 -> 0.25913414 | F13: =F5/L4 -> 0.24188559 | H13: Debt to assets | I13: =I5/I6 -> 0.52434327 | J13: =J5/J6 -> 0.5284901 | K13: =K5/K6 -> 0.5439524 | L13: =L5/L6 -> 0.5165608
B14: How efficiently a company uses equity money to generate income | H14: Percentage of total assets financed by debt
B16: ROA | C16: =C5/I6 -> 0.10073377 | D16: =D5/J6 -> 0.10898591 | E16: =E5/K6 -> 0.1181775 | F16: =F5/L6 -> 0.11693697
B17: How profitable a company is relative to its total assets

Sheet P&L
B1: EBITDA | C1: Net Income | D1: Gross Profit | E1: Total Revenue
A2: 2025 | B2: 102944934000 | C2: 49890741000 | D2: 244403717000 | E2: 1010803706000
A3: 2024 | B3: 100164445000 | C3: 53827384000 | D3: 230490223000 | E3: 957524496000
A4: 2023 | B4: 97020695000 | C4: 51589989000 | D4: 209774960000 | E4: 885739821000
A5: 2022 | B5: 89775599000 | C5: 48974184000 | D5: 190454535000 | E5: 818225636000

Sheet Balance
B1: Stockholders Equity | C1: Total Liabilities Net Minority Interest | D1: Total Assets
A2: 2025 | B2: 235580061000 | C2: 259693202000 | D2: 495273263000
A3: 2024 | B3: 232875469000 | C3: 261017596000 | D3: 493893065000
A4: 2023 | B4: 199086037000 | C4: 237460579000 | D4: 436546616000
A5: 2022 | B5: 202468383000 | C5: 216339988000 | D5: 418808371000

Sheet ROEROA
B1: Net profit margin | C1: ROE | D1: ROA
A2: 2025 | B2: 0.049357497 | C2: 0.21177828 | D2: 0.10073377
A3: 2024 | B3: 0.056215151 | C3: 0.23114235 | D3: 0.10898591
A4: 2023 | B4: 0.058245083 | C4: 0.25913414 | D4: 0.1181775
A5: 2022 | B5: 0.059854131 | C5: 0.24188559 | D5: 0.11693697

Sheet DEBT
B1: Debt to Equity | C1: Debt to assets
A2: 2025 | B2: 1.1023565 | C2: 0.52434327
A3: 2024 | B3: 1.1208462 | C3: 0.5284901
A4: 2023 | B4: 1.1927536 | C4: 0.5439524
A5: 2022 | B5: 1.0685125 | C5: 0.5165608
